muse_as_service/__init__.py
muse_as_service/app.py
muse_as_service/auth.py
muse_as_service/config.py
muse_as_service/endpoints.py
muse_as_service/utils.py
muse_as_service/client/__init__.py
muse_as_service/client/client.py
muse_as_service/database/__init__.py
muse_as_service/database/add_user.py
muse_as_service/database/database.py
muse_as_service/database/remove_user.py
muse_as_service/tokenizer/__init__.py
muse_as_service/tokenizer/tokenizer.py
muse_as_service-1.1.2.dist-info/LICENSE
muse_as_service-1.1.2.dist-info/METADATA
muse_as_service-1.1.2.dist-info/WHEEL
muse_as_service-1.1.2.dist-info/top_level.txt
muse_as_service-1.1.2.dist-info/RECORD
