Metadata-Version: 2.1
Name: muse-as-service
Version: 1.1.2
Summary: REST API for sentence tokenization and embedding using Multilingual Universal Sentence Encoder
Home-page: https://github.com/dayyass/muse-as-service
Author: Dani El-Ayyass
Author-email: dayyass@yandex.ru
License: UNKNOWN
Project-URL: Bug Tracker, https://github.com/dayyass/muse-as-service/issues
Platform: UNKNOWN
Classifier: Programming Language :: Python :: 3
Classifier: License :: OSI Approved :: MIT License
Classifier: Operating System :: OS Independent
Requires-Python: >=3.6
License-File: LICENSE
Requires-Dist: numpy (>=1.18.5)
Requires-Dist: requests (>=2.25.1)
